[
    {
        "title": "The New standard of Lithium Batteries",
        "category": "battery design",
        "alt": "blog new standard of batteries",
        "image": "/blogs/blog1.png",
        "link": "/blog/no1",
        "excerpt": "La Rochelle based battery manufacturer seasonal British flowers and UK producers in her beautiful and sustainable creations. This season, we worked with Flora to style Sunspel stores for Christmas, for which she produced eye-catching sustainably sourced wreaths."
    },
    {
        "title": "Energy Storage Systems.",
        "category": "applications",
        "alt": "Energy Storage Systems",
        "image": "/blogs/blog2.png",
        "link": "/blog/no2",
        "excerpt": "Energy Storage Systems."
    },
    {
        "title": "Van Life Battery Use",
        "category": "applications",
        "alt": "Van Life Battery Use",
        "image": "/blogs/blog3.png",
        "link": "/blog/no3",
        "excerpt": "Van Life Battery Use."
    },
    {
        "title": "Supporting Wind Power",
        "category": "news",
        "alt": "Supporting Wind Power",
        "image": "/blogs/blog3.png",
        "link": "/blog/no4",
        "excerpt": "Supporting Wind Power."
    },
    {
        "title": "Watercraft Electric Propulsion",
        "category": "design",
        "alt": "Watercraft Electric Propulsion",
        "image": "/blogs/blog2.png",
        "link": "/blog/no5",
        "excerpt": "Watercraft Electric Propulsion."
    },
    {
        "title": "Extending the Battery life of of a LFP battery",
        "category": "applications",
        "alt": "blog Extending the Battery life of of a LFP battery",
        "image": "/blogs/blog1.png",
        "link": "/blog/no6",
        "excerpt": "Extending the Battery life of of a LFP battery"
    },
    {
        "title": "Narrow Boats using LFP",
        "category": "applications",
        "alt": "blog Narrow Boats using LFP",
        "image": "/blogs/blog2.png",
        "link": "/blog/no7",
        "excerpt": "Narrow Boats using LFP."
    },
    {
        "title": "It is a long et a reader by the readable t is a long et a reader by the rea",
        "category": "applications",
        "alt": "blog new standard of closing",
        "image": "/blogs/blog2.png",
        "link": "/blog/sample",
        "excerpt": "London-bs and UK producers in her beautiful and sustainable creations. This season, we worked with Flora to style Sunspel stores for Christmas, for which she produced eye-catching sustainably sourced wreaths."
    }
  ]
